argo_metadata_validator/__init__.py
argo_metadata_validator/cli.py
argo_metadata_validator/constants.py
argo_metadata_validator/exceptions.py
argo_metadata_validator/models/float.py
argo_metadata_validator/models/platform.py
argo_metadata_validator/models/results.py
argo_metadata_validator/models/sensor.py
argo_metadata_validator/schema/0.2.0/argo.RBR.schema.json
argo_metadata_validator/schema/0.2.0/argo.SBE.schema.json
argo_metadata_validator/schema/0.2.0/argo.float.schema.json
argo_metadata_validator/schema/0.2.0/argo.platform.schema.json
argo_metadata_validator/schema/0.2.0/argo.sensor.schema.json
argo_metadata_validator/schema/0.2.0/argo.vendors.schema.json
argo_metadata_validator/schema/0.3.0/argo.MRV.schema.json
argo_metadata_validator/schema/0.3.0/argo.RBR.schema.json
argo_metadata_validator/schema/0.3.0/argo.SBE.schema.json
argo_metadata_validator/schema/0.3.0/argo.TRIOS.schema.json
argo_metadata_validator/schema/0.3.0/argo.float.schema.json
argo_metadata_validator/schema/0.3.0/argo.platform.schema.json
argo_metadata_validator/schema/0.3.0/argo.sensor.schema.json
argo_metadata_validator/schema/0.3.0/argo.vendors.schema.json
argo_metadata_validator/schema/0.4.0/argo.MRV.schema.json
argo_metadata_validator/schema/0.4.0/argo.RBR.schema.json
argo_metadata_validator/schema/0.4.0/argo.SBE.schema.json
argo_metadata_validator/schema/0.4.0/argo.TRIOS.schema.json
argo_metadata_validator/schema/0.4.0/argo.float.schema.json
argo_metadata_validator/schema/0.4.0/argo.platform.schema.json
argo_metadata_validator/schema/0.4.0/argo.sensor.schema.json
argo_metadata_validator/schema/0.4.0/argo.vendors.schema.json
argo_metadata_validator/schema_utils.py
argo_metadata_validator/utils.py
argo_metadata_validator/validation.py
argo_metadata_validator/vocab_utils.py
argo_metadata_validator-0.0.8.dist-info/LICENSE
argo_metadata_validator-0.0.8.dist-info/METADATA
argo_metadata_validator-0.0.8.dist-info/WHEEL
argo_metadata_validator-0.0.8.dist-info/entry_points.txt
argo_metadata_validator-0.0.8.dist-info/RECORD
