Metadata-Version: 2.3
Name: argo-metadata-validator
Version: 0.0.8
Summary: Validator for ARGO sensor metadata JSON
License: EUPL-1.2
Keywords: argo,metadata,validation
Author: Matt McCormack
Author-email: matcor@noc.ac.uk
Requires-Python: >=3.11,<4.0
Classifier: License :: OSI Approved :: European Union Public Licence 1.2 (EUPL 1.2)
Classifier: Programming Language :: Python :: 3
Classifier: Programming Language :: Python :: 3.11
Classifier: Programming Language :: Python :: 3.12
Classifier: Programming Language :: Python :: 3.13
Requires-Dist: click (>=8.2.1,<9.0.0)
Requires-Dist: importlib-metadata (==7.2.1)
Requires-Dist: jsonschema (>=4.25.1,<5.0.0)
Requires-Dist: poetry-dynamic-versioning (>=1.1.0,<2.0.0)
Requires-Dist: pydantic (>=2.11.9,<3.0.0)
Requires-Dist: referencing (>=0.36.2,<0.37.0)
Requires-Dist: requests (>=2.32.5,<3.0.0)
Project-URL: Repository, https://github.com/euroargodev/argo-metadata-validator
